[
    {
        "timestamp": "2026-03-09 18:33:01",
        "hyperparameters": {
            "upto_week": 18,
            "num_classes": 2,
            "paper_baseline": true,
            "binary_mode": "paper",
            "batch_size": 64,
            "epochs": 80,
            "execution_device": "gpu",
            "use_mixed_precision": false,
            "with_static": true,
            "use_clustering_features": true,
            "accumulated_uptow": true,
            "latent_d": 256,
            "num_heads": 8,
            "ff_dim": 128,
            "dropout": 0.3,
            "num_layers": 2,
            "static_hidden": [
                64,
                32
            ],
            "head_hidden": [
                256,
                128,
                64,
                32
            ],
            "learning_rate": 0.001,
            "clipnorm": 1.0,
            "reduce_lr_factor": 0.2,
            "reduce_lr_patience": 7,
            "reduce_lr_min_lr": 1e-06,
            "early_stopping_patience": 10,
            "focal_gamma": 2.5,
            "focal_alpha": [
                0.27,
                0.73
            ],
            "eval_test": false,
            "history_filename": null,
            "seed": null,
            "tune_threshold": false,
            "threshold_acc_min": 0.7,
            "threshold_prec_min": 0.55,
            "threshold_objective": "balanced_accuracy",
            "threshold_min": 0.15,
            "threshold_max": 0.75,
            "threshold_points": 601,
            "threshold_fallback": 0.5,
            "run_compare": true,
            "fast_search": false
        },
        "validation_metrics": {
            "loss": 0.020735908299684525,
            "accuracy": 0.9126478433609009,
            "balanced_accuracy": 0.8991956900304745,
            "auc_ovr": 0.9535228558989987,
            "precision": 0.849705304518664,
            "recall": 0.865,
            "f1_score": 0.8572844400396432
        },
        "test_metrics": {
            "accuracy": 0.9086005394066526,
            "balanced_accuracy": 0.8959226837943299,
            "precision": 0.83203125,
            "recall": 0.86497461928934,
            "f1_score": 0.8481831757093081,
            "auc_ovr": 0.9488526882834354
        },
        "test_evaluation": {
            "timestamp": "2026-03-09 18:39:16",
            "selected_threshold": null
        }
    }
]