[
    {
        "timestamp": "2026-03-07 14:37:51",
        "hyperparameters": {
            "upto_week": 28,
            "num_classes": 2,
            "paper_baseline": true,
            "binary_mode": "paper",
            "batch_size": 64,
            "epochs": 80,
            "execution_device": "gpu",
            "use_mixed_precision": false,
            "with_static": true,
            "use_clustering_features": true,
            "accumulated_uptow": true,
            "latent_d": 256,
            "num_heads": 8,
            "ff_dim": 128,
            "dropout": 0.3,
            "num_layers": 2,
            "static_hidden": [
                64,
                32
            ],
            "head_hidden": [
                256,
                128,
                64,
                32
            ],
            "learning_rate": 0.001,
            "clipnorm": 1.0,
            "reduce_lr_factor": 0.2,
            "reduce_lr_patience": 7,
            "reduce_lr_min_lr": 1e-06,
            "early_stopping_patience": 10,
            "focal_gamma": 2.5,
            "focal_alpha": [
                0.27,
                0.73
            ],
            "eval_test": false,
            "history_filename": null,
            "seed": null,
            "tune_threshold": false,
            "threshold_acc_min": 0.7,
            "threshold_prec_min": 0.55,
            "threshold_objective": "balanced_accuracy",
            "threshold_min": 0.15,
            "threshold_max": 0.75,
            "threshold_points": 601,
            "threshold_fallback": 0.5,
            "run_compare": true,
            "fast_search": false
        },
        "validation_metrics": {
            "loss": 0.009597844444215298,
            "accuracy": 0.9690815210342407,
            "balanced_accuracy": 0.9634082209656372,
            "auc_ovr": 0.9917098738581993,
            "precision": 0.949,
            "recall": 0.949,
            "f1_score": 0.949
        }
    },
    {
        "timestamp": "2026-03-07 17:46:43",
        "hyperparameters": {
            "upto_week": 28,
            "num_classes": 2,
            "paper_baseline": true,
            "binary_mode": "paper",
            "batch_size": 64,
            "epochs": 80,
            "execution_device": "gpu",
            "use_mixed_precision": false,
            "with_static": true,
            "use_clustering_features": true,
            "accumulated_uptow": true,
            "latent_d": 256,
            "num_heads": 8,
            "ff_dim": 128,
            "dropout": 0.3,
            "num_layers": 2,
            "static_hidden": [
                64,
                32
            ],
            "head_hidden": [
                256,
                128,
                64,
                32
            ],
            "learning_rate": 0.001,
            "clipnorm": 1.0,
            "reduce_lr_factor": 0.2,
            "reduce_lr_patience": 7,
            "reduce_lr_min_lr": 1e-06,
            "early_stopping_patience": 10,
            "focal_gamma": 2.5,
            "focal_alpha": [
                0.27,
                0.73
            ],
            "eval_test": false,
            "history_filename": null,
            "seed": null,
            "tune_threshold": false,
            "threshold_acc_min": 0.7,
            "threshold_prec_min": 0.55,
            "threshold_objective": "balanced_accuracy",
            "threshold_min": 0.15,
            "threshold_max": 0.75,
            "threshold_points": 601,
            "threshold_fallback": 0.5,
            "run_compare": true,
            "fast_search": false
        },
        "validation_metrics": {
            "loss": 0.009899516589939594,
            "accuracy": 0.9645346999168396,
            "balanced_accuracy": 0.9609934754240974,
            "auc_ovr": 0.9908012179208352,
            "precision": 0.9324191968658179,
            "recall": 0.952,
            "f1_score": 0.9421078673923801
        }
    },
    {
        "timestamp": "2026-03-07 18:09:17",
        "hyperparameters": {
            "upto_week": 28,
            "num_classes": 2,
            "paper_baseline": true,
            "binary_mode": "paper",
            "batch_size": 64,
            "epochs": 80,
            "execution_device": "gpu",
            "use_mixed_precision": false,
            "with_static": true,
            "use_clustering_features": true,
            "accumulated_uptow": true,
            "latent_d": 256,
            "num_heads": 8,
            "ff_dim": 128,
            "dropout": 0.3,
            "num_layers": 2,
            "static_hidden": [
                64,
                32
            ],
            "head_hidden": [
                256,
                128,
                64,
                32
            ],
            "learning_rate": 0.001,
            "clipnorm": 1.0,
            "reduce_lr_factor": 0.2,
            "reduce_lr_patience": 7,
            "reduce_lr_min_lr": 1e-06,
            "early_stopping_patience": 10,
            "focal_gamma": 2.5,
            "focal_alpha": [
                0.27,
                0.73
            ],
            "eval_test": false,
            "history_filename": null,
            "seed": null,
            "tune_threshold": false,
            "threshold_acc_min": 0.7,
            "threshold_prec_min": 0.55,
            "threshold_objective": "balanced_accuracy",
            "threshold_min": 0.15,
            "threshold_max": 0.75,
            "threshold_points": 601,
            "threshold_fallback": 0.5,
            "run_compare": true,
            "fast_search": false
        },
        "validation_metrics": {
            "loss": 0.009544349275529385,
            "accuracy": 0.9699909090995789,
            "balanced_accuracy": 0.9640606785558938,
            "auc_ovr": 0.9906241844280121,
            "precision": 0.9518555667001003,
            "recall": 0.949,
            "f1_score": 0.9504256384576866
        }
    },
    {
        "timestamp": "2026-03-07 19:57:25",
        "hyperparameters": {
            "upto_week": 28,
            "num_classes": 2,
            "paper_baseline": true,
            "binary_mode": "paper",
            "batch_size": 64,
            "epochs": 80,
            "execution_device": "gpu",
            "use_mixed_precision": false,
            "with_static": true,
            "use_clustering_features": true,
            "accumulated_uptow": true,
            "latent_d": 256,
            "num_heads": 8,
            "ff_dim": 128,
            "dropout": 0.3,
            "num_layers": 2,
            "static_hidden": [
                64,
                32
            ],
            "head_hidden": [
                256,
                128,
                64,
                32
            ],
            "learning_rate": 0.001,
            "clipnorm": 1.0,
            "reduce_lr_factor": 0.2,
            "reduce_lr_patience": 7,
            "reduce_lr_min_lr": 1e-06,
            "early_stopping_patience": 10,
            "focal_gamma": 2.5,
            "focal_alpha": [
                0.27,
                0.73
            ],
            "eval_test": false,
            "history_filename": null,
            "seed": null,
            "tune_threshold": false,
            "threshold_acc_min": 0.7,
            "threshold_prec_min": 0.55,
            "threshold_objective": "balanced_accuracy",
            "threshold_min": 0.15,
            "threshold_max": 0.75,
            "threshold_points": 601,
            "threshold_fallback": 0.5,
            "run_compare": true,
            "fast_search": false
        },
        "validation_metrics": {
            "loss": 0.009629903361201286,
            "accuracy": 0.9699909090995789,
            "balanced_accuracy": 0.962083079599826,
            "auc_ovr": 0.9912701174423663,
            "precision": 0.9582909460834181,
            "recall": 0.942,
            "f1_score": 0.9500756429652042
        }
    },
    {
        "timestamp": "2026-03-07 21:45:55",
        "hyperparameters": {
            "upto_week": 28,
            "num_classes": 2,
            "paper_baseline": true,
            "binary_mode": "paper",
            "batch_size": 64,
            "epochs": 80,
            "execution_device": "gpu",
            "use_mixed_precision": false,
            "with_static": true,
            "use_clustering_features": true,
            "accumulated_uptow": true,
            "latent_d": 256,
            "num_heads": 8,
            "ff_dim": 128,
            "dropout": 0.3,
            "num_layers": 2,
            "static_hidden": [
                64,
                32
            ],
            "head_hidden": [
                256,
                128,
                64,
                32
            ],
            "learning_rate": 0.001,
            "clipnorm": 1.0,
            "reduce_lr_factor": 0.2,
            "reduce_lr_patience": 7,
            "reduce_lr_min_lr": 1e-06,
            "early_stopping_patience": 10,
            "focal_gamma": 2.5,
            "focal_alpha": [
                0.27,
                0.73
            ],
            "eval_test": false,
            "history_filename": null,
            "seed": null,
            "tune_threshold": false,
            "threshold_acc_min": 0.7,
            "threshold_prec_min": 0.55,
            "threshold_objective": "balanced_accuracy",
            "threshold_min": 0.15,
            "threshold_max": 0.75,
            "threshold_points": 601,
            "threshold_fallback": 0.5,
            "run_compare": true,
            "fast_search": false
        },
        "validation_metrics": {
            "loss": 0.009581467136740685,
            "accuracy": 0.9651409387588501,
            "balanced_accuracy": 0.9605809047411917,
            "auc_ovr": 0.9926150500217485,
            "precision": 0.9368213228035538,
            "recall": 0.949,
            "f1_score": 0.9428713363139593
        },
        "test_metrics": {
            "accuracy": 0.9580712788259959,
            "balanced_accuracy": 0.9511014379812919,
            "precision": 0.9246987951807228,
            "recall": 0.934077079107505,
            "f1_score": 0.929364278506559,
            "auc_ovr": 0.9831267149355749
        },
        "test_evaluation": {
            "timestamp": "2026-03-07 22:00:31",
            "selected_threshold": null
        }
    }
]