{
  "1": {
    "label": "CRITICAL_RISK_INACTIVE",
    "name": "Riesgo crítico (inactivos)",
    "rank_worst_to_best": 0,
    "n": 3525,
    "withdrawn_pct": 87.91489361702128,
    "success_pct": 0.22695035460992907
  },
  "3": {
    "label": "STANDARD_PROFILE",
    "name": "Perfil intermedio A",
    "rank_worst_to_best": 1,
    "n": 2772,
    "withdrawn_pct": 65.18759018759019,
    "success_pct": 1.6594516594516595
  },
  "4": {
    "label": "METHODICAL_EXPLORER",
    "name": "Perfil intermedio B",
    "rank_worst_to_best": 2,
    "n": 10760,
    "withdrawn_pct": 25.817843866171003,
    "success_pct": 43.83828996282528
  },
  "2": {
    "label": "CONSISTENT_GOOD",
    "name": "Perfil intermedio C",
    "rank_worst_to_best": 3,
    "n": 3173,
    "withdrawn_pct": 18.436810589347623,
    "success_pct": 57.29593444689568
  },
  "0": {
    "label": "STRATEGIC_HIGH_PERFORMER",
    "name": "Alto rendimiento (estratégico)",
    "rank_worst_to_best": 4,
    "n": 7444,
    "withdrawn_pct": 5.037614185921548,
    "success_pct": 86.53949489521763
  }
}